{
	"id": "33222225-9e8c-47c4-ad3e-125739f5e357",
	"name": "New_Env",
	"values": [
		{
			"key": "url",
			"value": "http://116.203.27.46:5002",
			"enabled": true
		},
		{
			"key": "token",
			"value": "",
			"enabled": true
		},
		{
			"key": "salary",
			"value": "800",
			"enabled": true
		},
		{
			"key": "name",
			"value": "Pavel",
			"enabled": true
		},
		{
			"key": "age",
			"value": "27",
			"enabled": true
		},
		{
			"key": "Cur_ID",
			"value": "",
			"enabled": true
		}
	],
	"_postman_variable_scope": "environment",
	"_postman_exported_at": "2021-05-06T11:10:32.661Z",
	"_postman_exported_using": "Postman/7.36.5"
}